WinTimer/Timer.py
WinTimer/__init__.py
WinTimer-1.1.1.2.dist-info/METADATA
WinTimer-1.1.1.2.dist-info/WHEEL
WinTimer-1.1.1.2.dist-info/top_level.txt
WinTimer-1.1.1.2.dist-info/RECORD
