Metadata-Version: 2.1
Name: WinTimer
Version: 1.1.1.2
Summary: Timer
Home-page: https://github.com/PS218909/
Author: Piyush
Author-email: somanip409@gmail.com
License: MIT
Platform: UNKNOWN
Requires-Python: >=3.6
